byted_overpass_videocut_data_crawlai/__init__.py
byted_overpass_videocut_data_crawlai-0.0.1.dist-info/METADATA
byted_overpass_videocut_data_crawlai-0.0.1.dist-info/WHEEL
byted_overpass_videocut_data_crawlai-0.0.1.dist-info/top_level.txt
byted_overpass_videocut_data_crawlai-0.0.1.dist-info/RECORD
